odoo/addons/account_check_printing_report_base/README.rst
odoo/addons/account_check_printing_report_base/__init__.py
odoo/addons/account_check_printing_report_base/__manifest__.py
odoo/addons/account_check_printing_report_base/data/report_paperformat.xml
odoo/addons/account_check_printing_report_base/i18n/account_check_printing_report_base.pot
odoo/addons/account_check_printing_report_base/i18n/es.po
odoo/addons/account_check_printing_report_base/i18n/pt.po
odoo/addons/account_check_printing_report_base/models/__init__.py
odoo/addons/account_check_printing_report_base/models/account_journal.py
odoo/addons/account_check_printing_report_base/models/account_payment.py
odoo/addons/account_check_printing_report_base/models/res_company.py
odoo/addons/account_check_printing_report_base/readme/CONFIGURE.rst
odoo/addons/account_check_printing_report_base/readme/CONTRIBUTORS.rst
odoo/addons/account_check_printing_report_base/readme/DESCRIPTION.rst
odoo/addons/account_check_printing_report_base/readme/ROADMAP.rst
odoo/addons/account_check_printing_report_base/readme/USAGE.rst
odoo/addons/account_check_printing_report_base/report/__init__.py
odoo/addons/account_check_printing_report_base/report/account_check_writing_report.xml
odoo/addons/account_check_printing_report_base/report/check_print.py
odoo/addons/account_check_printing_report_base/report/lang.py
odoo/addons/account_check_printing_report_base/security/ir.model.access.csv
odoo/addons/account_check_printing_report_base/static/description/icon.png
odoo/addons/account_check_printing_report_base/static/description/index.html
odoo/addons/account_check_printing_report_base/tests/__init__.py
odoo/addons/account_check_printing_report_base/tests/test_check_printing_report.py
odoo/addons/account_check_printing_report_base/tests/test_num2words_lang_solution.py
odoo/addons/account_check_printing_report_base/views/account_journal_view.xml
odoo/addons/account_check_printing_report_base/views/report_check_base.xml
odoo14_addon_account_check_printing_report_base-14.0.1.0.1.dev5.dist-info/METADATA
odoo14_addon_account_check_printing_report_base-14.0.1.0.1.dev5.dist-info/WHEEL
odoo14_addon_account_check_printing_report_base-14.0.1.0.1.dev5.dist-info/top_level.txt
odoo14_addon_account_check_printing_report_base-14.0.1.0.1.dev5.dist-info/RECORD
