Metadata-Version: 2.1
Name: odoo14-addon-account-check-printing-report-base
Version: 14.0.1.0.1.dev5
Summary: Account Check Printing Report Base
Home-page: https://github.com/OCA/account-payment
Author: ForgeFlow,Serpent Consulting Services Pvt. Ltd.,Ursa Information Systems,Odoo Community Association (OCA)
Author-email: support@odoo-community.org
License: AGPL-3
Platform: UNKNOWN
Classifier: Programming Language :: Python
Classifier: Framework :: Odoo
Classifier: Framework :: Odoo :: 14.0
Classifier: License :: OSI Approved :: GNU Affero General Public License v3
Requires-Python: >=3.6
Requires-Dist: num2words
Requires-Dist: odoo14-addon-report-wkhtmltopdf-param
Requires-Dist: odoo <14.1dev,>=14.0a
